[{"web_pages":["http://www.espam-formationuc.org/"],"name":"Espam Formation University","alpha_two_code":"BJ","state-province":null,"domains":["espam-formationuc.org"],"country":"Benin"},{"web_pages":["http://www.hnaubenin.org/"],"name":"Houdegbe North American University Benin","alpha_two_code":"BJ","state-province":null,"domains":["hnaubenin.org"],"country":"Benin"},{"web_pages":["http://www.uac.bj/"],"name":"Université d'Abomey-Calavi (UAC)","alpha_two_code":"BJ","state-province":null,"domains":["uac.bj"],"country":"Benin"}]