[{"web_pages":["http://www.tabari.ac.ir/"],"name":"Tabari Institute of Higher Education","alpha_two_code":"IR","state-province":"Mazandaran","domains":["tabari.ac.ir"],"country":"Iran"},{"web_pages":["https://www.acmt.ac.ir/"],"name":"Amirkabir College of Management & Technology","alpha_two_code":"IR","state-province":"Tehran","domains":["acmt.ac.ir"],"country":"Iran"},{"web_pages":["http://www.adiban.ac.ir/"],"name":"Adiban Institute of Higher Education","alpha_two_code":"IR","state-province":"Semnan","domains":["adiban.ac.ir"],"country":"Iran"},{"web_pages":["https://www.ajums.ac.ir/"],"name":"Ahvaz Jondishapur University of Medical Sciences","alpha_two_code":"IR","state-province":"Khuzestan","domains":["ajums.ac.ir"],"country":"Iran"},{"web_pages":["http://aliabadiau.ac.ir/"],"name":"Islamic Azad University, Aliabad","alpha_two_code":"IR","state-province":"Golestan","domains":["aliabadiau.ac.ir"],"country":"Iran"},{"web_pages":["http://miu.ac.ir/"],"name":"Al-Mustafa International University","alpha_two_code":"IR","state-province":"Qom","domains":["miu.ac.ir"],"country":"Iran"},{"web_pages":["http://www.arakmu.ac.ir/"],"name":"Arak University of Medical Sciences","alpha_two_code":"IR","state-province":"Markazi","domains":["arakmu.ac.ir"],"country":"Iran"},{"web_pages":["http://www.araku.ac.ir/"],"name":"Arak University","alpha_two_code":"IR","state-province":"Markazi","domains":["araku.ac.ir"],"country":"Iran"},{"web_pages":["http://www.arakut.ac.ir/"],"name":"Arak University of Technology","alpha_two_code":"IR","state-province":"Markazi","domains":["arakut.ac.ir"],"country":"Iran"},{"web_pages":["https://www.kut.ac.ir/"],"name":"Kermanshah University of Technology","alpha_two_code":"IR","state-province":"Kermanshah","domains":["kut.ac.ir"],"country":"Iran"},{"web_pages":["http://www.art.ac.ir/"],"name":"Art University","alpha_two_code":"IR","state-province":"Tehran","domains":["art.ac.ir"],"country":"Iran"},{"web_pages":["http://www.arums.ac.ir/"],"name":"Ardabil University of Medical Sciences","alpha_two_code":"IR","state-province":"Ardabil","domains":["arums.ac.ir"],"country":"Iran"},{"web_pages":["http://www.atu.ac.ir/"],"name":"Allameh Tabatabaie University","alpha_two_code":"IR","state-province":"Tehran","domains":["atu.ac.ir"],"country":"Iran"},{"web_pages":["http://www.aums.ac.ir/"],"name":"Ahvaz University of Medical Sciences","alpha_two_code":"IR","state-province":"Khuzestan","domains":["aums.ac.ir"],"country":"Iran"},{"web_pages":["http://www.aut.ac.ir/"],"name":"Amirkabir University of Technology","alpha_two_code":"IR","state-province":"Tehran","domains":["aut.ac.ir"],"country":"Iran"},{"web_pages":["http://www.azad.ac.ir/"],"name":"Islamic Azad University, Tehran South","alpha_two_code":"IR","state-province":"Tehran","domains":["azad.ac.ir"],"country":"Iran"},{"web_pages":["http://www.alzahra.ac.ir/"],"name":"Alzahra University","alpha_two_code":"IR","state-province":"Tehran","domains":["alzahra.ac.ir"],"country":"Iran"},{"web_pages":["http://www.basu.ac.ir/"],"name":"Bu Ali Sina University","alpha_two_code":"IR","state-province":"Hamedan","domains":["basu.ac.ir"],"country":"Iran"},{"web_pages":["http://www.bihe.org/"],"name":"Baha'i Institute for Higher Education","alpha_two_code":"IR","state-province":null,"domains":["bihe.org"],"country":"Iran"},{"web_pages":["http://www.birjand.ac.ir/"],"name":"Birjand University","alpha_two_code":"IR","state-province":null,"domains":["birjand.ac.ir"],"country":"Iran"},{"web_pages":["http://www.bmsu.ac.ir/"],"name":"Baqiyatallah University of Medical Sciences","alpha_two_code":"IR","state-province":"Tehran","domains":["bmsu.ac.ir"],"country":"Iran"},{"web_pages":["http://www.bojnourdiau.ac.ir/"],"name":"Islamic Azad University, Bojnourd","alpha_two_code":"IR","state-province":"North Khorasan","domains":["bojnourdiau.ac.ir"],"country":"Iran"},{"web_pages":["http://www.bpums.ac.ir/"],"name":"Bushehr University of Medical Sciences","alpha_two_code":"IR","state-province":"Bushehr","domains":["bpums.ac.ir"],"country":"Iran"},{"web_pages":["http://www.bums.ac.ir/"],"name":"Birjand University of Medical Sciences","alpha_two_code":"IR","state-province":"South Khorasan","domains":["bums.ac.ir"],"country":"Iran"},{"web_pages":["http://scu.ac.ir/"],"name":"Shahid Chamran University of Ahvaz","alpha_two_code":"IR","state-province":"Khuzestan","domains":["scu.ac.ir"],"country":"Iran"},{"web_pages":["http://www.dehaghan.ac.ir/"],"name":"Islamic Azad University, Dehaghan","alpha_two_code":"IR","state-province":"Isfahan","domains":["dehaghan.ac.ir"],"country":"Iran"},{"web_pages":["http://www.delijanpnu.ac.ir/"],"name":"Delijan Payame Noor University","alpha_two_code":"IR","state-province":"Markazi","domains":["delijanpnu.ac.ir"],"country":"Iran"},{"web_pages":["http://www.deylaman.ac.ir/"],"name":"Deylaman Institute of Higher Education","alpha_two_code":"IR","state-province":"Gilan","domains":["deylaman.ac.ir"],"country":"Iran"},{"web_pages":["http://www.du.ac.ir/"],"name":"Damghan University","alpha_two_code":"IR","state-province":"Semnan","domains":["du.ac.ir"],"country":"Iran"},{"web_pages":["http://www.falavarjan.ac.ir/"],"name":"Islamic Azad University, Falavarjan","alpha_two_code":"IR","state-province":"Isfahan","domains":["falavarjan.ac.ir"],"country":"Iran"},{"web_pages":["http://www.fsriau.ac.ir/"],"name":"Islamic Azad University, Fars Science & Research Branch","alpha_two_code":"IR","state-province":"Fars","domains":["fsriau.ac.ir"],"country":"Iran"},{"web_pages":["http://www.fums.ac.ir/"],"name":"Fasa Faculty of Medical Sciences","alpha_two_code":"IR","state-province":"Fars","domains":["fums.ac.ir"],"country":"Iran"},{"web_pages":["http://www.gau.ac.ir/"],"name":"Gorgan University","alpha_two_code":"IR","state-province":"Golestan","domains":["gau.ac.ir"],"country":"Iran"},{"web_pages":["http://www.gmu.ac.ir/"],"name":"Gonabad University of Medical Sciences","alpha_two_code":"IR","state-province":"Razavi Khorasan","domains":["gmu.ac.ir"],"country":"Iran"},{"web_pages":["http://www.gorganiau.ir/"],"name":"Islamic Azad University, Gorgan","alpha_two_code":"IR","state-province":"Golestan","domains":["gorganiau.ir"],"country":"Iran"},{"web_pages":["http://www.goums.ac.ir/"],"name":"Golestan University of Medical Sciences","alpha_two_code":"IR","state-province":"Golestan","domains":["goums.ac.ir"],"country":"Iran"},{"web_pages":["http://www.guilan.ac.ir/"],"name":"University of Guilan","alpha_two_code":"IR","state-province":"Gilan","domains":["guilan.ac.ir"],"country":"Iran"},{"web_pages":["http://www.gums.ac.ir/"],"name":"Guilan University of Medical Sciences","alpha_two_code":"IR","state-province":"Gilan","domains":["gums.ac.ir"],"country":"Iran"},{"web_pages":["http://www.hormozgan.ac.ir/"],"name":"University of Hormozgan","alpha_two_code":"IR","state-province":"Hormozgan","domains":["hormozgan.ac.ir"],"country":"Iran"},{"web_pages":["http://www.hums.ac.ir/"],"name":"Hormozgan University of Medical Sciences","alpha_two_code":"IR","state-province":"Hormozgan","domains":["hums.ac.ir"],"country":"Iran"},{"web_pages":["http://www.hyrcania.ac.ir/"],"name":"Hyrcania Institute of Higher Education","alpha_two_code":"IR","state-province":null,"domains":["hyrcania.ac.ir"],"country":"Iran"},{"web_pages":["http://www.iasbs.ac.ir/"],"name":"Zanjan Institute for Advanced Studies in Basic Sciences","alpha_two_code":"IR","state-province":"Zanjan","domains":["iasbs.ac.ir"],"country":"Iran"},{"web_pages":["http://www.iau-ahar.ac.ir/"],"name":"Islamic Azad University, Ahar","alpha_two_code":"IR","state-province":"East Azerbaijan","domains":["iau-ahar.ac.ir"],"country":"Iran"},{"web_pages":["http://www.iau-arak.ac.ir/"],"name":"Islamic Azad University, Arak","alpha_two_code":"IR","state-province":"Markazi","domains":["iau-arak.ac.ir"],"country":"Iran"},{"web_pages":["http://www.iauardabil.ac.ir/"],"name":"Islamic Azad University, Ardabil","alpha_two_code":"IR","state-province":"Ardabil","domains":["iauardabil.ac.ir"],"country":"Iran"},{"web_pages":["http://www.iauba.ac.ir/"],"name":"Islamic Azad University, Bandar Abbas","alpha_two_code":"IR","state-province":"Hormozgan","domains":["iauba.ac.ir"],"country":"Iran"},{"web_pages":["http://www.iaubos.ac.ir/"],"name":"Islamic Azad University, Bostanabad","alpha_two_code":"IR","state-province":"East Azerbaijan","domains":["iaubos.ac.ir"],"country":"Iran"},{"web_pages":["http://www.iau-boukan.ac.ir"],"name":"Islamic Azad University, Boukan","alpha_two_code":"IR","state-province":"West Azerbaijan","domains":["iau-boukan.ac.ir"],"country":"Iran"},{"web_pages":["http://www.iauctb.ac.ir/"],"name":"Islamic Azad University, Central Tehran Branch","alpha_two_code":"IR","state-province":"Tehran","domains":["iauctb.ac.ir"],"country":"Iran"},{"web_pages":["http://www.iau-garmsar.ac.ir/"],"name":"Islamic Azad University, Garmsar","alpha_two_code":"IR","state-province":"Semnan","domains":["iau-garmsar.ac.ir"],"country":"Iran"},{"web_pages":["http://www.iauh.ac.ir/"],"name":"Islamic Azad University, Hamedan","alpha_two_code":"IR","state-province":"Hamedan","domains":["iauh.ac.ir"],"country":"Iran"},{"web_pages":["http://www.iauk.ac.ir/"],"name":"Islamic Azad University, Kerman","alpha_two_code":"IR","state-province":"Kerman","domains":["iauk.ac.ir"],"country":"Iran"},{"web_pages":["http://www.iaukb.ir/"],"name":"Islamic Azad University, Karaj","alpha_two_code":"IR","state-province":"Alborz","domains":["iaukb.ir"],"country":"Iran"},{"web_pages":["http://www.iau-lahijan.ac.ir/"],"name":"Islamic Azad University, Lahijan","alpha_two_code":"IR","state-province":"Gilan","domains":["iau-lahijan.ac.ir"],"country":"Iran"},{"web_pages":["http://www.iaumajlesi.ac.ir/"],"name":"Islamic Azad University, Majlesi","alpha_two_code":"IR","state-province":"Isfahan","domains":["iaumajlesi.ac.ir"],"country":"Iran"},{"web_pages":["http://www.iaumehriz.com/"],"name":"Islamic Azad University, Mehriz","alpha_two_code":"IR","state-province":"Yazd","domains":["iaumehriz.com"],"country":"Iran"},{"web_pages":["http://www.iaun.ac.ir/"],"name":"Islamic Azad University, Najafabad","alpha_two_code":"IR","state-province":"Isfahan","domains":["iaun.ac.ir"],"country":"Iran"},{"web_pages":["http://www.iauq.ac.ir/"],"name":"Islamic Azad University, Quchan","alpha_two_code":"IR","state-province":"Razavi Khorasan","domains":["iauq.ac.ir"],"country":"Iran"},{"web_pages":["http://www.iauro.ac.ir/"],"name":"Islamic Azad University, Region One","alpha_two_code":"IR","state-province":null,"domains":["iauro.ac.ir"],"country":"Iran"},{"web_pages":["http://www.iau-saveh.ac.ir/"],"name":"Islamic Azad University, Saveh","alpha_two_code":"IR","state-province":"Markazi","domains":["iau-saveh.ac.ir"],"country":"Iran"},{"web_pages":["http://www.iausdj.ac.ir/"],"name":"Islamic Azad University, Sanandaj","alpha_two_code":"IR","state-province":"Kurdistan","domains":["iausdj.ac.ir"],"country":"Iran"},{"web_pages":["http://www.iaushab.ac.ir/"],"name":"Islamic Azad University, Shabestar","alpha_two_code":"IR","state-province":"East Azerbaijan","domains":["iaushab.ac.ir"],"country":"Iran"},{"web_pages":["http://www.iau-shahrood.ac.ir/"],"name":"Islamic Azad University, Shahrood","alpha_two_code":"IR","state-province":"Semnan","domains":["iau-shahrood.ac.ir"],"country":"Iran"},{"web_pages":["http://www.iaushiraz.ac.ir/"],"name":"Islamic Azad University, Shiraz","alpha_two_code":"IR","state-province":"Fars","domains":["iaushiraz.ac.ir"],"country":"Iran"},{"web_pages":["http://www.iau-shirvan.ac.ir/"],"name":"Islamic Azad University, Shirvan","alpha_two_code":"IR","state-province":"North Khorasan","domains":["iau-shirvan.ac.ir"],"country":"Iran"},{"web_pages":["http://www.iausr.ac.ir/"],"name":"Islamic Azad University, Shahr-e-rey","alpha_two_code":"IR","state-province":"Tehran","domains":["iausr.ac.ir"],"country":"Iran"},{"web_pages":["http://www.iaut.ac.ir/"],"name":"Islamic Azad University, Tabriz","alpha_two_code":"IR","state-province":"East Azerbaijan","domains":["iaut.ac.ir"],"country":"Iran"},{"web_pages":["http://www.iautb.ac.ir/"],"name":"Islamic Azad University, Tafresh","alpha_two_code":"IR","state-province":"Markazi","domains":["iautb.ac.ir"],"country":"Iran"},{"web_pages":["http://www.iautmu.ac.ir/"],"name":"Islamic Azad University, Theran Medical","alpha_two_code":"IR","state-province":"Theran","domains":["iautmu.ac.ir"],"country":"Iran"},{"web_pages":["http://www.iau-tnb.ac.ir/"],"name":"Islamic Azad University, North Tehran","alpha_two_code":"IR","state-province":"Tehran","domains":["iau-tnb.ac.ir"],"country":"Iran"},{"web_pages":["http://www.iauvaramin.ac.ir/"],"name":"Islamic Azad University, Varamin","alpha_two_code":"IR","state-province":"Tehran","domains":["iauvaramin.ac.ir"],"country":"Iran"},{"web_pages":["http://www.iauyazd.ac.ir/"],"name":"Islamic Azad University, Yazd","alpha_two_code":"IR","state-province":"Yazd","domains":["iauyazd.ac.ir"],"country":"Iran"},{"web_pages":["http://www.ikiu.ac.ir/"],"name":"Imam Khomeini International University","alpha_two_code":"IR","state-province":"Qazvin","domains":["ikiu.ac.ir"],"country":"Iran"},{"web_pages":["http://www.ilam.ac.ir/"],"name":"Ilam University","alpha_two_code":"IR","state-province":"Ilam","domains":["ilam.ac.ir"],"country":"Iran"},{"web_pages":["http://www.imamreza.ac.ir/"],"name":"Imam Reza University","alpha_two_code":"IR","state-province":"Razavi Khorasan","domains":["imamreza.ac.ir"],"country":"Iran"},{"web_pages":["http://www.isu.ac.ir/"],"name":"Imam Sadegh University","alpha_two_code":"IR","state-province":"Tehran","domains":["isu.ac.ir"],"country":"Iran"},{"web_pages":["http://www.iums.ac.ir/"],"name":"Iran University of Medical Sciences","alpha_two_code":"IR","state-province":"Tehran","domains":["iums.ac.ir"],"country":"Iran"},{"web_pages":["http://www.iust.ac.ir/"],"name":"Iran University of Science and Technology Tehran","alpha_two_code":"IR","state-province":"Tehran","domains":["iust.ac.ir"],"country":"Iran"},{"web_pages":["http://www.iut.ac.ir/"],"name":"Isfahan University of Technology","alpha_two_code":"IR","state-province":"Isfahan","domains":["iut.ac.ir"],"country":"Iran"},{"web_pages":["http://www.jami.ac.ir/"],"name":"Jami Institute of Technology","alpha_two_code":"IR","state-province":"Isfahan","domains":["jami.ac.ir"],"country":"Iran"},{"web_pages":["http://www.janahiau.ac.ir/"],"name":"Islamic Azad University, Janah","alpha_two_code":"IR","state-province":"Hormozgan","domains":["janahiau.ac.ir"],"country":"Iran"},{"web_pages":["http://www.jums.ac.ir/"],"name":"Jahrom University of Medical Sciences","alpha_two_code":"IR","state-province":"Fars","domains":["jums.ac.ir"],"country":"Iran"},{"web_pages":["http://www.kamalolmolk.ac.ir/"],"name":"Kamal-Ol-Molk University","alpha_two_code":"IR","state-province":"Mazandaran","domains":["kamalolmolk.ac.ir"],"country":"Iran"},{"web_pages":["http://www.karuniversity.com/"],"name":"Kar University","alpha_two_code":"IR","state-province":"Qazvin","domains":["karuniversity.com"],"country":"Iran"},{"web_pages":["http://www.kashanu.ac.ir/"],"name":"Kashan University","alpha_two_code":"IR","state-province":"Isfahan","domains":["kashanu.ac.ir"],"country":"Iran"},{"web_pages":["http://www.kau.ac.ir/"],"name":"Islamic Azad University, Kazerun","alpha_two_code":"IR","state-province":"Fars","domains":["kau.ac.ir"],"country":"Iran"},{"web_pages":["http://www.kaums.ac.ir/"],"name":"Kashan University of Medical Sciences","alpha_two_code":"IR","state-province":"Isfahan","domains":["kaums.ac.ir"],"country":"Iran"},{"web_pages":["http://www.kgut.ac.ir/"],"name":"Kerman Graduate University of Technology","alpha_two_code":"IR","state-province":"Kerman","domains":["kgut.ac.ir"],"country":"Iran"},{"web_pages":["http://www.khuisf.ac.ir/"],"name":"Islamic Azad University, Khorasgan","alpha_two_code":"IR","state-province":"Isfahan","domains":["khuisf.ac.ir"],"country":"Iran"},{"web_pages":["http://www.kish.ac.ir/"],"name":"Sharif University of Technology, Kish Campus","alpha_two_code":"IR","state-province":"Hormozgan","domains":["kish.ac.ir"],"country":"Iran"},{"web_pages":["http://km.isfpnu.ac.ir/"],"name":"Khomeinishahr Payame Noor University","alpha_two_code":"IR","state-province":"Isfahan","domains":["km.isfpnu.ac.ir"],"country":"Iran"},{"web_pages":["http://www.kmu.ac.ir/"],"name":"Kerman University of Medical Sciences","alpha_two_code":"IR","state-province":"Kerman","domains":["kmu.ac.ir"],"country":"Iran"},{"web_pages":["http://www.kntu.ac.ir/"],"name":"Khajeh Nasir Toosi University of Technology","alpha_two_code":"IR","state-province":"Tehran","domains":["kntu.ac.ir"],"country":"Iran"},{"web_pages":["http://www.kums.ac.ir/"],"name":"Kermanshah University of Medical Sciences","alpha_two_code":"IR","state-province":"Kermanshah","domains":["kums.ac.ir"],"country":"Iran"},{"web_pages":["http://teh-lavasan.pnu.ac.ir/"],"name":"Payam Noor University Lavasan","alpha_two_code":"IR","state-province":"Tehran","domains":["teh-lavasan.pnu.ac.ir"],"country":"Iran"},{"web_pages":["http://www.lu.ac.ir/"],"name":"Lorestan University","alpha_two_code":"IR","state-province":"Lorestan","domains":["lu.ac.ir"],"country":"Iran"},{"web_pages":["http://www.lums.ac.ir/"],"name":"Lorestan University of Medical Sciences","alpha_two_code":"IR","state-province":"Lorestan","domains":["lums.ac.ir"],"country":"Iran"},{"web_pages":["http://www.mahshahriau.ac.ir/"],"name":"Islamic Azad University, Mahshar","alpha_two_code":"IR","state-province":"Khuzestan","domains":["mahshahriau.ac.ir"],"country":"Iran"},{"web_pages":["http://www.malayeru.ac.ir/"],"name":"Malayer University","alpha_two_code":"IR","state-province":"Hamadan","domains":["malayeru.ac.ir"],"country":"Iran"},{"web_pages":["http://www.malekanpnu.ac.ir/"],"name":"Malekan Payame Noor University","alpha_two_code":"IR","state-province":"East Azerbaijan","domains":["malekanpnu.ac.ir"],"country":"Iran"},{"web_pages":["http://www.mamasaniiau.ac.ir/"],"name":"Mamasani University of Technology","alpha_two_code":"IR","state-province":"Fars","domains":["mamasaniiau.ac.ir"],"country":"Iran"},{"web_pages":["http://www.mau.ac.ir/"],"name":"Islamic Azad University, Mobarakeh","alpha_two_code":"IR","state-province":"Isfahan","domains":["mau.ac.ir"],"country":"Iran"},{"web_pages":["http://www.maybod.ac.ir/"],"name":"Islamic Azad University, Maybod","alpha_two_code":"IR","state-province":"Yazd","domains":["maybod.ac.ir"],"country":"Iran"},{"web_pages":["http://www.mazums.ac.ir/"],"name":"Mazandaran University of Medical Science","alpha_two_code":"IR","state-province":"Mazandaran","domains":["mazums.ac.ir"],"country":"Iran"},{"web_pages":["http://www.medilam.hbi.ir/"],"name":"Ilam University of Medical Sciences","alpha_two_code":"IR","state-province":"Ilam","domains":["medilam.hbi.ir"],"country":"Iran"},{"web_pages":["http://www.medsab.ac.ir/"],"name":"Sabzevar School of Medical Sciences","alpha_two_code":"IR","state-province":"Razavi Khorasan","domains":["medsab.ac.ir"],"country":"Iran"},{"web_pages":["http://www.modares.ac.ir/"],"name":"Tarbiat Modares University","alpha_two_code":"IR","state-province":"Tehran","domains":["modares.ac.ir"],"country":"Iran"},{"web_pages":["http://www.mofidu.ac.ir/"],"name":"Mofid University","alpha_two_code":"IR","state-province":"Qom","domains":["mofidu.ac.ir"],"country":"Iran"},{"web_pages":["http://www.mshdiau.ac.ir/"],"name":"Islamic Azad University, Mashhad","alpha_two_code":"IR","state-province":"Razavi Khorasan","domains":["mshdiau.ac.ir"],"country":"Iran"},{"web_pages":["http://www.mubabol.ac.ir/"],"name":"Babol University of Medical Sciences","alpha_two_code":"IR","state-province":"Mazandaran","domains":["mubabol.ac.ir"],"country":"Iran"},{"web_pages":["http://www.mui.ac.ir/"],"name":"Isfahan University of Medical Sciences","alpha_two_code":"IR","state-province":"Isfahan","domains":["mui.ac.ir"],"country":"Iran"},{"web_pages":["http://www.muk.ac.ir/"],"name":"Kurdistan University of Medical Sciences","alpha_two_code":"IR","state-province":"Kurdistan","domains":["muk.ac.ir"],"country":"Iran"},{"web_pages":["http://www.mums.ac.ir/"],"name":"Mashhad University of Medical Sciences","alpha_two_code":"IR","state-province":"Razavi Khorasan","domains":["mums.ac.ir"],"country":"Iran"},{"web_pages":["http://www.muq.ac.ir/"],"name":"Qom University of Medical Sciences","alpha_two_code":"IR","state-province":"Qom","domains":["muq.ac.ir"],"country":"Iran"},{"web_pages":["http://www.najafabad-uast.ac.ir/"],"name":"Najaf Abad University of Applied Science and Technology","alpha_two_code":"IR","state-province":"Isfahan","domains":["najafabad-uast.ac.ir"],"country":"Iran"},{"web_pages":["http://www.nit.ac.ir/"],"name":"Babol Noshirvani University of Technology","alpha_two_code":"IR","state-province":"Mazandaran","domains":["nit.ac.ir"],"country":"Iran"},{"web_pages":["http://www.pgu.ac.ir/"],"name":"Persian Gulf University","alpha_two_code":"IR","state-province":"Bushehr","domains":["pgu.ac.ir"],"country":"Iran"},{"web_pages":["http://www.piau.ac.ir/"],"name":"Islamic Azad University, Parand","alpha_two_code":"IR","state-province":"Tehran","domains":["piau.ac.ir"],"country":"Iran"},{"web_pages":["http://www.pnu.ac.ir/"],"name":"Payame Noor University","alpha_two_code":"IR","state-province":"Tehran","domains":["pnu.ac.ir"],"country":"Iran"},{"web_pages":["http://www.pnum.ac.ir/"],"name":"University of Mashhad Payame Noor","alpha_two_code":"IR","state-province":"Razavi Khorasan","domains":["pnum.ac.ir"],"country":"Iran"},{"web_pages":["http://www.pnut.ac.ir/"],"name":"Payame Noor University, Tafresh","alpha_two_code":"IR","state-province":"Markazi","domains":["pnut.ac.ir"],"country":"Iran"},{"web_pages":["http://www.put.ac.ir/"],"name":"Petroleum University of Technology","alpha_two_code":"IR","state-province":"Khuzestan","domains":["put.ac.ir"],"country":"Iran"},{"web_pages":["http://www.pwit.ac.ir/"],"name":"Power and Water Institute of Technology","alpha_two_code":"IR","state-province":null,"domains":["pwit.ac.ir"],"country":"Iran"},{"web_pages":["http://qiau.ac.ir/"],"name":"Islamic Azad University, Qazvin","alpha_two_code":"IR","state-province":"Qazvin","domains":["qiau.ac.ir"],"country":"Iran"},{"web_pages":["http://www.qom.ac.ir/"],"name":"Qom University","alpha_two_code":"IR","state-province":"Qom","domains":["qom.ac.ir"],"country":"Iran"},{"web_pages":["http://www.qom-iau.ac.ir/"],"name":"Islamic Azad University, Qom","alpha_two_code":"IR","state-province":"Qom","domains":["qom-iau.ac.ir"],"country":"Iran"},{"web_pages":["http://www.qums.ac.ir/"],"name":"Qazvin University of Medical Sciences","alpha_two_code":"IR","state-province":"Qazvin","domains":["qums.ac.ir"],"country":"Iran"},{"web_pages":["http://www.qut.ac.ir/"],"name":"Qom University of Technology","alpha_two_code":"IR","state-province":"Qom","domains":["qut.ac.ir"],"country":"Iran"},{"web_pages":["http://www.raghebisf.ac.ir/"],"name":"Ragheb Esfahani University","alpha_two_code":"IR","state-province":"Isfahan","domains":["raghebisf.ac.ir"],"country":"Iran"},{"web_pages":["http://www.razi.ac.ir/"],"name":"Razi University","alpha_two_code":"IR","state-province":"Kermanshah","domains":["razi.ac.ir"],"country":"Iran"},{"web_pages":["http://www.riau.ac.ir/"],"name":"Islamic Azad University, Roodehen","alpha_two_code":"IR","state-province":"Tehran","domains":["riau.ac.ir"],"country":"Iran"},{"web_pages":["http://www.rums.ac.ir/"],"name":"Rafsanjan University of Medical Sciences","alpha_two_code":"IR","state-province":"Kerman","domains":["rums.ac.ir"],"country":"Iran"},{"web_pages":["http://www.sadjad.ac.ir/"],"name":"Sadjad Institute of Technology","alpha_two_code":"IR","state-province":"Razavi Khorasan","domains":["sadjad.ac.ir"],"country":"Iran"},{"web_pages":["http://www.sadra.ac.ir/"],"name":"Sadra University","alpha_two_code":"IR","state-province":"Tehran","domains":["sadra.ac.ir"],"country":"Iran"},{"web_pages":["http://www.sbmu.ac.ir/"],"name":"Shahid Beheshti University of Medical Sciences","alpha_two_code":"IR","state-province":"Tehran","domains":["sbmu.ac.ir"],"country":"Iran"},{"web_pages":["http://www.sbu.ac.ir/"],"name":"Shahid Beheshti University","alpha_two_code":"IR","state-province":"Tehran","domains":["sbu.ac.ir"],"country":"Iran"},{"web_pages":["http://www.sdi.ac.ir/"],"name":"Daneshestan Institute of Higher Education","alpha_two_code":"IR","state-province":"Markazi","domains":["sdi.ac.ir"],"country":"Iran"},{"web_pages":["http://www.semnan.ac.ir/"],"name":"Semnan University","alpha_two_code":"IR","state-province":"Semnan","domains":["semnan.ac.ir"],"country":"Iran"},{"web_pages":["http://www.semnaniau.ac.ir/"],"name":"Islamic Azad University, Semnan","alpha_two_code":"IR","state-province":"Semnan","domains":["semnaniau.ac.ir"],"country":"Iran"},{"web_pages":["http://www.sem-ums.ac.ir/"],"name":"Semnan University of Medical Sciences","alpha_two_code":"IR","state-province":"Semnan","domains":["sem-ums.ac.ir"],"country":"Iran"},{"web_pages":["http://www.ses.ac.ir/"],"name":"School of Economic Sciences","alpha_two_code":"IR","state-province":null,"domains":["ses.ac.ir"],"country":"Iran"},{"web_pages":["http://www.shahed.ac.ir/"],"name":"Shahed University","alpha_two_code":"IR","state-province":"Tehran","domains":["shahed.ac.ir"],"country":"Iran"},{"web_pages":["http://www.shahroodut.ac.ir/"],"name":"Shahrood University of Technology","alpha_two_code":"IR","state-province":"Semnan","domains":["shahroodut.ac.ir"],"country":"Iran"},{"web_pages":["http://www.shahryariau.ac.ir/"],"name":"Islamic Azad University, Shahryar","alpha_two_code":"IR","state-province":"Tehran","domains":["shahryariau.ac.ir"],"country":"Iran"},{"web_pages":["http://www.sharif.ac.ir/"],"name":"Sharif University of Technology","alpha_two_code":"IR","state-province":"Tehran","domains":["sharif.ac.ir"],"country":"Iran"},{"web_pages":["http://www.shbu.ac.ir/"],"name":"Sheikh Bahaei University","alpha_two_code":"IR","state-province":"Isfahan","domains":["shbu.ac.ir"],"country":"Iran"},{"web_pages":["http://www.shirazu.ac.ir/"],"name":"Shiraz University","alpha_two_code":"IR","state-province":"Fars","domains":["shirazu.ac.ir"],"country":"Iran"},{"web_pages":["http://www.shmu.ac.ir/"],"name":"Shahrood University of Medical Sciences","alpha_two_code":"IR","state-province":"Semnan","domains":["shmu.ac.ir"],"country":"Iran"},{"web_pages":["http://www.shomal.ac.ir/"],"name":"Shomal University","alpha_two_code":"IR","state-province":"Mazandaran","domains":["shomal.ac.ir"],"country":"Iran"},{"web_pages":["http://www.sku.ac.ir/"],"name":"Shahrekord University","alpha_two_code":"IR","state-province":"Chaharmahal and Bakhtiari","domains":["sku.ac.ir"],"country":"Iran"},{"web_pages":["http://www.skums.ac.ir/"],"name":"Shahrekord University of Medical Sciences","alpha_two_code":"IR","state-province":"Chaharmahal and Bakhtiari","domains":["skums.ac.ir"],"country":"Iran"},{"web_pages":["http://www.sowmesaraiau.ac.ir/"],"name":"Islamic Azad University, Someh Sara","alpha_two_code":"IR","state-province":"Gilan","domains":["sowmesaraiau.ac.ir"],"country":"Iran"},{"web_pages":["http://www.spnu.ac.ir/"],"name":"Shiraz Payamnoor University","alpha_two_code":"IR","state-province":"Fars","domains":["spnu.ac.ir"],"country":"Iran"},{"web_pages":["http://www.srbiau.ac.ir/"],"name":"Islamic Azad University, Tehran Science & Research Branch","alpha_two_code":"IR","state-province":"Tehran","domains":["srbiau.ac.ir"],"country":"Iran"},{"web_pages":["http://www.srttu.edu/"],"name":"Shahid Rajaee Teacher Training University","alpha_two_code":"IR","state-province":"Tehran","domains":["srttu.edu"],"country":"Iran"},{"web_pages":["http://www.ssu.ac.ir/"],"name":"Yazd Medical University","alpha_two_code":"IR","state-province":"Yazd","domains":["ssu.ac.ir"],"country":"Iran"},{"web_pages":["http://www.sttu.ac.ir/"],"name":"Sabzevar Teacher Training University","alpha_two_code":"IR","state-province":"Razavi Khorasan","domains":["sttu.ac.ir"],"country":"Iran"},{"web_pages":["http://www.sums.ac.ir/"],"name":"Shiraz University of Medical Sciences","alpha_two_code":"IR","state-province":"Fars","domains":["sums.ac.ir"],"country":"Iran"},{"web_pages":["http://www.sut.ac.ir/"],"name":"Sahand University of Technology","alpha_two_code":"IR","state-province":"East Azerbaijan","domains":["sut.ac.ir"],"country":"Iran"},{"web_pages":["http://www.sutech.ac.ir/"],"name":"Shiraz University of Technology","alpha_two_code":"IR","state-province":"Fars","domains":["sutech.ac.ir"],"country":"Iran"},{"web_pages":["http://www.tabriziau.ac.ir/"],"name":"Tabriz Islamic Art University","alpha_two_code":"IR","state-province":"East Azerbaijan","domains":["tabriziau.ac.ir"],"country":"Iran"},{"web_pages":["http://www.tabrizu.ac.ir/"],"name":"Tabriz University","alpha_two_code":"IR","state-province":"East Azerbaijan","domains":["tabrizu.ac.ir"],"country":"Iran"},{"web_pages":["http://www.tbzmed.ac.ir/"],"name":"Tabriz University of Medical Sciences","alpha_two_code":"IR","state-province":"East Azerbaijan","domains":["tbzmed.ac.ir"],"country":"Iran"},{"web_pages":["http://www.tct.ac.ir/"],"name":"Tabriz College of Technology","alpha_two_code":"IR","state-province":"East Azerbaijan","domains":["tct.ac.ir"],"country":"Iran"},{"web_pages":["http://www.thums.ac.ir/"],"name":"Torbat Heydarieh University of Medical Sciences","alpha_two_code":"IR","state-province":"Razavi Khorasan","domains":["thums.ac.ir"],"country":"Iran"},{"web_pages":["http://www.tiau.ac.ir/"],"name":"Takestan Islamic Azad University","alpha_two_code":"IR","state-province":"Qazvin","domains":["tiau.ac.ir"],"country":"Iran"},{"web_pages":["http://www.tmu.ac.ir/"],"name":"Tehran University of Teacher Training","alpha_two_code":"IR","state-province":"Tehran","domains":["tmu.ac.ir"],"country":"Iran"},{"web_pages":["http://www.tums.ac.ir/"],"name":"Tehran University of Medical Sciences","alpha_two_code":"IR","state-province":"Tehran","domains":["tums.ac.ir"],"country":"Iran"},{"web_pages":["http://www.uast.ac.ir/"],"name":"University of Applied Science and Technology","alpha_two_code":"IR","state-province":"Tehran","domains":["uast.ac.ir"],"country":"Iran"},{"web_pages":["http://www.ucna.info/"],"name":"University College of Nabi Akram","alpha_two_code":"IR","state-province":"East Azerbaijan","domains":["ucna.info"],"country":"Iran"},{"web_pages":["http://www.ui.ac.ir/"],"name":"Isfahan University","alpha_two_code":"IR","state-province":"Isfahan","domains":["ui.ac.ir"],"country":"Iran"},{"web_pages":["http://www.uk.ac.ir/"],"name":"Shahid Bahonar University of Kerman","alpha_two_code":"IR","state-province":"Kerman","domains":["uk.ac.ir"],"country":"Iran"},{"web_pages":["http://www.uma.ac.ir/"],"name":"University of Mohaghegh Ardabili","alpha_two_code":"IR","state-province":"Ardabili","domains":["uma.ac.ir"],"country":"Iran"},{"web_pages":["http://www.um.ac.ir/"],"name":"Ferdowsi University of Mashhad","alpha_two_code":"IR","state-province":"Razavi Khorasan","domains":["um.ac.ir"],"country":"Iran"},{"web_pages":["http://www.umsha.ac.ir/"],"name":"Hamadan University of Medical Sciences","alpha_two_code":"IR","state-province":"Hamadan","domains":["umsha.ac.ir"],"country":"Iran"},{"web_pages":["http://www.umsu.ac.ir/"],"name":"Urmia University of Medical Sciences","alpha_two_code":"IR","state-province":"West Azarbaijan","domains":["umsu.ac.ir"],"country":"Iran"},{"web_pages":["http://www.umz.ac.ir/"],"name":"Mazandaran University of Iran","alpha_two_code":"IR","state-province":"Mazandaran","domains":["umz.ac.ir"],"country":"Iran"},{"web_pages":["http://www.uok.ac.ir/"],"name":"University of Kurdistan","alpha_two_code":"IR","state-province":"Kurdistan","domains":["uok.ac.ir"],"country":"Iran"},{"web_pages":["http://www.uoz.ac.ir/"],"name":"Zabol University","alpha_two_code":"IR","state-province":"Sistan and Baluchestan","domains":["uoz.ac.ir"],"country":"Iran"},{"web_pages":["http://www.urmia.ac.ir/"],"name":"Urmia University","alpha_two_code":"IR","state-province":"West Azerbaijan","domains":["urmia.ac.ir"],"country":"Iran"},{"web_pages":["http://www.usb.ac.ir/"],"name":"Sistan and Baluchestan University","alpha_two_code":"IR","state-province":"Sistan and Baluchestan","domains":["usb.ac.ir"],"country":"Iran"},{"web_pages":["http://www.usc.ac.ir/"],"name":"University of Science and Culture","alpha_two_code":"IR","state-province":"Tehran","domains":["usc.ac.ir"],"country":"Iran"},{"web_pages":["http://www.ustmb.ac.ir/"],"name":"Mazandaran University of Science & Technology","alpha_two_code":"IR","state-province":"Mazandaran","domains":["ustmb.ac.ir"],"country":"Iran"},{"web_pages":["http://www.uswr.ac.ir/"],"name":"University of Social Welfare and Rehabilitation Sciences","alpha_two_code":"IR","state-province":"Tehran","domains":["uswr.ac.ir"],"country":"Iran"},{"web_pages":["http://www.ut.ac.ir/"],"name":"University of Tehran","alpha_two_code":"IR","state-province":"Tehran","domains":["ut.ac.ir"],"country":"Iran"},{"web_pages":["http://www.uut.ac.ir/"],"name":"Urmia University of Technology","alpha_two_code":"IR","state-province":"West Azerbaijan","domains":["uut.ac.ir"],"country":"Iran"},{"web_pages":["http://www.vru.ac.ir/"],"name":"Vali-e-Asr University of Rafsanjan","alpha_two_code":"IR","state-province":"Kerman","domains":["vru.ac.ir"],"country":"Iran"},{"web_pages":["http://www.yazduni.ac.ir/"],"name":"Yazd University","alpha_two_code":"IR","state-province":"Yazd","domains":["yazduni.ac.ir"],"country":"Iran"},{"web_pages":["http://www.yu.ac.ir/"],"name":"Yasuj University","alpha_two_code":"IR","state-province":"Kohgiluyeh and Boyer-Ahmad","domains":["yu.ac.ir"],"country":"Iran"},{"web_pages":["http://www.yums.ac.ir/"],"name":"Yasuj University of Medical Sciences","alpha_two_code":"IR","state-province":"Kohgiluyeh and Boyer-Ahmad","domains":["yums.ac.ir"],"country":"Iran"},{"web_pages":["http://www.zdmu.ac.ir/"],"name":"Zahedan University of Medical Sciences","alpha_two_code":"IR","state-province":"Sistan and Baluchestan","domains":["zdmu.ac.ir"],"country":"Iran"},{"web_pages":["http://www.znu.ac.ir/"],"name":"Zanjan University","alpha_two_code":"IR","state-province":"Zanjan","domains":["znu.ac.ir"],"country":"Iran"},{"web_pages":["http://www.zums.ac.ir/"],"name":"Zanjan University of Medical Sciences","alpha_two_code":"IR","state-province":"Zanjan","domains":["zums.ac.ir"],"country":"Iran"}]